[
  {
    "title": "bodyguard 3",
    "poster": "https://raw.githubusercontent.com/jhonie07/nontongratis/main/MV5BYmEyYzlmNWEtYmQzYy00MzQ4LTlkOTAtNTBmOTA4NWJmOWQ4XkEyXkFqcGc%40._V1_.jpg,
    "embed": "https://www.dailymotion.com/embed/video/x9e1lse",
    "genre": "Action",
    "year": "2025"
  },
  {
    "title": "Spider-Man: No Way Home",
    "poster": "https://image.tmdb.org/t/p/w500/spiderman.jpg",
    "embed": "https://www.dailymotion.com/embed/video/x7example",
    "genre": "Action",
    "year": "2021"
  }
]
